vessel_voxelizer/__init__.py
vessel_voxelizer/_vessel_vox.pyd
vessel_voxelizer/utils.py
vessel_voxelizer-0.0.1.dist-info/METADATA
vessel_voxelizer-0.0.1.dist-info/WHEEL
vessel_voxelizer-0.0.1.dist-info/licenses/LICENSE
vessel_voxelizer-0.0.1.dist-info/RECORD
