Metadata-Version: 2.1
Name: vessel-voxelizer
Version: 0.0.1
Summary: GPU accelerated (fuzzy) voxelization of vascular structures.
Author-Email: Fabian Schneider <fabianschneider2609@gmail.com>
Project-URL: Homepage, https://github.com/faberno/vessel_voxelizer
Requires-Python: >=3.8
Requires-Dist: numpy
Requires-Dist: pandas
Requires-Dist: matplotlib
